Workbook

Sheet Instructions
A1: Overview of tabs in excel file
A3: Cost Guide Tables: The tables that are referenced in the Transmission Cost Estimation Guide.
A6: Exploratory cost estimate tab: User enters in all the scopes of work for the potential project.
A9: Line and substation exploratory example tabs: Provides details of example line and substation calculations.
A12: Costs over time estimate tab: Estimated life-cycle costs for the first 20 years of project in-service are calcuated.
A15: Convert to Nominal tab: Convert current year cost to "nominal" cost to construct using both an inflation faor and an estimated cash flow by year.
A18: MISO Cost Estimation Guide for MTEP25
A19: For more information and background on MISO's cost estimation approach, see MISO's Cost Estimation Guide for MTEP25 posted on MISO's website: http://www.misoenergy.org/planning/transmissionplanning
A23: Disclaimer
A24: This document is prepared for informational purposes only to support MISO planning staff in developing cost estimates and deriving benefit-to-cost ratios for solutions proposed for inclusion in the MISO Transmission Expansion Plan (MTEP). MISO’s cost estimation approach is based on staff experience, vendor consultation, industry practice, and stakeholder feedback. MISO makes every effort to develop its cost estimates from the most accurate and appropriate assumptions and information available at that time. However, MISO cannot and does not guarantee the accuracy of information, assumptions, judgments, or opinions contained herein or derived therefrom. MISO may revise or terminate this document at any time at its discretion without notice. MISO’s cost estimation assumptions are not an indication or a direction for how any particular project shall be designed or built.

Sheet Cost Guide Tables
F1: MISO Transmission Cost Estimation Guide - Supplemental Tables
F2: For MTEP25
A4: Table 2.1: Land Cost per acre
B5: State | C5: Pasture | D5: Crop | E5: Urban/ Suburban | F5: Acquisition | G5: Regulatory & permitting
B6: Arkansas | C6: 3400.8 | D6: 10202.4 | E6: 17004 | F6: 14817.153 | G6: 3086.907
B7: Illinois | C7: 4128.8 | D7: 12386.4 | E7: 20644 | F7: 14817.153 | G7: 3086.907
B8: Indiana | C8: 2776.8 | D8: 8330.4 | E8: 13884 | F8: 14817.153 | G8: 3086.907
B9: Iowa | C9: 3640 | D9: 10920 | E9: 18200 | F9: 14817.153 | G9: 3086.907
B10: Kentucky | C10: 3920.8 | D10: 11762.4 | E10: 19604 | F10: 14817.153 | G10: 3086.907
B11: Louisiana | C11: 3494.4 | D11: 10483.2 | E11: 17472 | F11: 14817.153 | G11: 3086.907
B12: Michigan | C12: 3088.8 | D12: 9266.4 | E12: 15444 | F12: 14817.153 | G12: 3086.907
B13: Minnesota | C13: 2298.4 | D13: 6895.2 | E13: 11492 | F13: 14817.153 | G13: 10310.269
B14: Mississippi | C14: 3244.8 | D14: 9734.4 | E14: 16224 | F14: 14817.153 | G14: 3086.907
B15: Missouri | C15: 2756 | D15: 8268 | E15: 13780 | F15: 14817.153 | G15: 3086.907
B16: Montana | C16: 925.6 | D16: 2776.8 | E16: 4628 | F16: 14817.153 | G16: 3086.907
B17: North Dakota | C17: 1092 | D17: 3276 | E17: 5460 | F17: 14817.153 | G17: 5155.1347
... B20: Wisconsin | C20: 3328 | D20: 9984 | E20: 16640 | F20: 14817.153 | G20: 10310.269
A22: Table 2.2-1: AC transmission - steel pole - single circuit
B23: Voltage class | C23: 69 kV | D23: 115 kV | E23: 138 kV | F23: 161 kV | G23: 230 kV | H23: 345 kV | I23: 500 kV | J23: 765 kV
B24: Tangent structure
B25: Steel weight (lbs.) | C25: 7000 | D25: 7900 | E25: 8400 | F25: 9300 | G25: 11100 | H25: 22300 | I25: 35100 | J25: 52800
B26: Foundation size (Cu. Yd) | C26: 5.5 | D26: 6 | E26: 8 | F26: 9 | G26: 13 | H26: 21 | I26: 41 | J26: 60
B27: Material | C27: 19252.106 | D27: 21727.377 | E27: 23102.528 | F27: 25577.798 | G27: 30528.34 | H27: 61331.71 | I27: 96535.562 | J27: 145217.12
B28: Installation | C28: 24927.845 | D28: 28132.854 | E28: 29913.414 | F28: 33118.423 | G28: 39528.44 | H28: 79412.993 | I28: 124677.38 | J28: 188026.12
B29: Hardware | C29: 4973.9859 | D29: 5802.7828 | E29: 6218.3859 | F29: 7047.1828 | G29: 8289.1734 | H29: 11091.181 | I29: 12142.838 | J29: 24365.183
B30: Foundation | C30: 8898.7246 | D30: 9707.0425 | E30: 12942.723 | F30: 14560.564 | G30: 21031.925 | H30: 33974.649 | I30: 66331.457 | J30: 97069.22
B31: Running angle structure
B32: Steel weight (lbs.) | C32: 11600 | D32: 13000 | E32: 13900 | F32: 15300 | G32: 18300 | H32: 37900 | I32: 59700 | J32: 149000
B33: Foundation size (Cu. Yd) | C33: 9 | D33: 10.5 | E33: 13 | F33: 14 | G33: 19.5 | H33: 30 | I33: 54.5 | J33: 85
B34: Material | C34: 31903.491 | D34: 35753.912 | E34: 38229.183 | F34: 42079.604 | G34: 50330.507 | H34: 104236.4 | I34: 164192.96 | J34: 409798.52
B35: Installation | C35: 41309.001 | D35: 46294.57 | E35: 49499.578 | F35: 54485.148 | G35: 65168.51 | H35: 134966.48 | I35: 212598.91 | J35: 530603.81
B36: Hardware | C36: 4973.9859 | D36: 5802.7828 | E36: 6218.3859 | F36: 7047.1828 | G36: 8289.1734 | H36: 11091.181 | I36: 12142.838 | J36: 24365.183
B37: Foundation | C37: 14560.564 | D37: 16987.927 | E37: 21031.925 | F37: 22649.766 | G37: 31548.49 | H37: 48535.213 | I37: 88172.905 | J37: 137514.03
B38: Non-angled deadend structure
B39: Steel weight (lbs.) | C39: 14000 | D39: 15800 | E39: 16800 | F39: 18600 | G39: 22200 | H39: 42400 | I39: 66700 | J39: 154675
B40: Foundation size (Cu. Yd) | C40: 11 | D40: 12 | E40: 15 | F40: 16.5 | G40: 22.5 | H40: 33.5 | I40: 60 | J40: 160
B41: Material | C41: 38504.213 | D41: 43454.754 | E41: 46205.055 | F41: 51155.597 | G41: 61056.68 | H41: 116612.76 | I41: 183445.07 | J41: 425406.48
B42: Installation | C42: 49855.691 | D42: 56265.708 | E42: 59826.829 | F42: 66236.846 | G42: 79056.881 | H42: 150991.52 | I42: 237526.75 | J42: 550813.17
B43: Hardware | C43: 9807.0282 | D43: 11441.734 | E43: 12259.689 | F43: 13893.19 | G43: 16345.85 | H43: 39865.371 | I43: 62710.289 | J43: 97460.731
B44: Foundation | C44: 17796.245 | D44: 19414.085 | E44: 24267.606 | F44: 26694.969 | G44: 36402.012 | H44: 54198.256 | I44: 97070.425 | J44: 258850.85
B45: Angled deadend structure
B46: Steel weight (lbs.) | C46: 20400 | D46: 23000 | E46: 24500 | F46: 27100 | G46: 32400 | H46: 48100 | I46: 80700 | J46: 154675
B47: Foundation size (Cu. Yd) | C47: 15 | D47: 16.5 | E47: 20 | F47: 21.5 | G47: 29 | H47: 41.5 | I47: 72 | J47: 160
B48: Material | C48: 56106.139 | D48: 63256.921 | E48: 67382.372 | F48: 74533.155 | G48: 89109.749 | H48: 132289.47 | I48: 221949.28 | J48: 425406.48
B49: Installation | C49: 72646.863 | D49: 81905.777 | E49: 87247.458 | F49: 96506.372 | G49: 115380.31 | H49: 171289.91 | I49: 287382.44 | J49: 550813.17
B50: Hardware | C50: 9807.0282 | D50: 11441.734 | E50: 12259.689 | F50: 13893.19 | G50: 16345.85 | H50: 39865.371 | I50: 62710.289 | J50: 97460.731
B51: Foundation | C51: 24267.606 | D51: 26694.969 | E51: 32356.808 | F51: 34784.171 | G51: 46917.372 | H51: 67140.98 | I51: 116484.51 | J51: 258850.85
A54: Table 2.2-2: AC transmission – steel tower – single circuit
B55: Voltage class | C55: 69 kV | D55: 115 kV | E55: 138 kV | F55: 161 kV | G55: 230 kV | H55: 345 kV | I55: 500 kV | J55: 765 kV
B56: Tangent structure
B57: Steel weight (lbs.) | C57: 6100 | D57: 6900 | E57: 7300 | F57: 8100 | G57: 10100 | H57: 20300 | I57: 27000 | J57: 34320
B58: Foundation size (Cu. Yd) | C58: 8.5 | D58: 11.5 | E58: 13.5 | F58: 14.5 | G58: 15.5 | H58: 19.5 | I58: 33.5 | J58: 39
B59: Material | C59: 14005.662 | D59: 15842.47 | E59: 16760.874 | F59: 18597.682 | G59: 23189.702 | H59: 46609.006 | I59: 61992.274 | J59: 94391.801
B60: Installation | C60: 18135.219 | D60: 20513.539 | E60: 21702.699 | F60: 24081.019 | G60: 30026.819 | H60: 60350.398 | I60: 80268.298 | J60: 122216.39
B61: Hardware | C61: 4973.9859 | D61: 5802.7828 | E61: 6218.3859 | F61: 7047.1828 | G61: 8289.1734 | H61: 11091.181 | I61: 12142.838 | J61: 24365.183
B62: Foundation | C62: 13752.246 | D62: 18605.767 | E62: 21841.448 | F62: 23459.288 | G62: 25077.129 | H62: 31548.49 | I62: 54198.256 | J62: 63094.572
B63: Running angle structures
B64: Steel weight (lbs.) | C64: 9200 | D64: 10400 | E64: 11000 | F64: 12200 | G64: 15200 | H64: 30500 | I64: 39800 | J64: 89400
B65: Foundation size (Cu. Yd) | C65: 16 | D65: 19 | E65: 19.5 | F65: 22 | G65: 24.5 | H65: 39 | I65: 72.5 | J65: 81
B66: Material | C66: 21123.293 | D66: 23878.505 | E66: 25256.111 | F66: 28011.324 | G66: 34899.354 | H66: 70028.309 | I66: 91381.203 | J66: 245879.36
B67: Installation | C67: 27350.679 | D67: 30918.159 | E67: 32701.899 | F67: 36269.379 | G67: 45188.079 | H67: 90673.977 | I67: 118321.42 | J67: 318362.08
B68: Hardware | C68: 4973.9859 | D68: 5802.7828 | E68: 6218.3859 | F68: 7047.1828 | G68: 8289.1734 | H68: 11091.181 | I68: 12142.838 | J68: 24365.183
B69: Foundation | C69: 25885.447 | D69: 30738.968 | E69: 31548.49 | F69: 35592.489 | G69: 39637.693 | H69: 63095.776 | I69: 117294.03 | J69: 131042.66
B70: Non-angled deadend structure
B71: Steel weight (lbs.) | C71: 10400 | D71: 11700 | E71: 12400 | F71: 13800 | G71: 17200 | H71: 34500 | I71: 45900 | J71: 108273
B72: Foundation size (Cu. Yd) | C72: 21.5 | D72: 25 | E72: 25.5 | F72: 28.5 | G72: 34 | H72: 48.5 | I72: 96 | J72: 180
B73: Material | C73: 23878.505 | D73: 26863.319 | E73: 28470.526 | F73: 31684.94 | G73: 39491.374 | H73: 79212.35 | I73: 105386.87 | J73: 297785.15
B74: Installation | C74: 30918.159 | D74: 34783.459 | E74: 36863.959 | F74: 41026.019 | G74: 51133.879 | H74: 102565.58 | I74: 136456.64 | J74: 385568.69
B75: Hardware | C75: 9807.0282 | D75: 11441.734 | E75: 12259.689 | F75: 13893.19 | G75: 16345.85 | H75: 39865.371 | I75: 62710.289 | J75: 24365.183
B76: Foundation | C76: 34784.171 | D76: 40446.01 | E76: 41255.533 | F76: 46109.054 | G76: 55006.574 | H76: 78465.863 | I76: 155312.68 | J76: 258850.85
B77: Angled deadend structure
B78: Steel weight (lbs.) | C78: 13400 | D78: 15200 | E78: 16100 | F78: 17800 | G78: 22200 | H78: 44700 | I78: 59400 | J78: 108273
B79: Foundation size (Cu. Yd) | C79: 33.5 | D79: 38 | E79: 39 | F79: 43 | G79: 52 | H79: 90 | I79: 176 | J79: 180
B80: Material | C80: 30766.536 | D80: 34899.354 | E80: 36965.763 | F80: 40868.98 | G80: 50971.425 | H80: 102631.65 | I80: 136383 | J80: 297785.15
B81: Installation | C81: 39836.859 | D81: 45188.079 | E81: 47864.219 | F81: 52917.618 | G81: 65998.378 | H81: 132889.16 | I81: 176590.25 | J81: 385568.69
B82: Hardware | C82: 9807.0282 | D82: 11441.734 | E82: 12259.689 | F82: 13893.19 | G82: 16345.85 | H82: 39865.371 | I82: 62710.289 | J82: 24365.183
B83: Foundation | C83: 54198.256 | D83: 61477.936 | E83: 63095.776 | F83: 69567.138 | G83: 84127.702 | H83: 145605.64 | I83: 284739.91 | J83: 258850.85
A85: Table 2.2-3: AC transmission – steel pole – double circuit
B86: Voltage class | C86: 69 kV | D86: 115 kV | E86: 138 kV | F86: 161 kV | G86: 230 kV | H86: 345 kV
B87: Tangent structure
B88: Steel weight (lbs.) | C88: 11300 | D88: 12700 | E88: 13500 | F88: 14900 | G88: 18600 | H88: 36000
B89: Foundation size (Cu. Yd) | C89: 8 | D89: 10 | E89: 14.5 | F89: 17.5 | G89: 23 | H89: 46.5
B90: Material | C90: 31078.4 | D90: 34928.822 | E90: 37129.062 | F90: 40979.484 | G90: 51155.597 | H90: 99010.833
B91: Installation | C91: 40240.665 | D91: 45226.234 | E91: 48075.13 | F91: 53060.699 | G91: 66236.846 | H91: 128200.35
B92: Hardware | C92: 9682.9496 | D92: 11297.176 | E92: 12103.085 | F92: 13717.311 | G92: 16138.651 | H92: 21716.165
B93: Foundation | C93: 12942.723 | D93: 16178.404 | E93: 23459.288 | F93: 28312.81 | G93: 37210.33 | H93: 75230.182
B94: Running angle structures
B95: Steel weight (lbs.) | C95: 15000 | D95: 16800 | E95: 17900 | F95: 19700 | G95: 24600 | H95: 47700
B96: Foundation size (Cu. Yd) | C96: 13 | D96: 15.5 | E96: 21.5 | F96: 25.5 | G96: 32.5 | H96: 61
B97: Material | C97: 41254.514 | D97: 46205.055 | E97: 49230.386 | F97: 54180.928 | G97: 67657.402 | H97: 131189.35
B98: Installation | C98: 53416.811 | D98: 59826.829 | E98: 63744.061 | F98: 70154.079 | G98: 87603.571 | H98: 169865.46
B99: Hardware | C99: 9682.9496 | D99: 11297.176 | E99: 12103.085 | F99: 13717.311 | G99: 16138.651 | H99: 21716.165
B100: Foundation | C100: 21031.925 | D100: 25077.129 | E100: 34784.171 | F100: 41255.533 | G100: 52580.416 | H100: 98688.265
B101: Non-angled deadend structure
B102: Steel weight (lbs.) | C102: 16700 | D102: 18700 | E102: 19900 | F102: 22000 | G102: 27400 | H102: 54000
B103: Foundation size (Cu. Yd) | C103: 15.5 | D103: 18.5 | E103: 25 | F103: 29.5 | G103: 37 | H103: 68.5
B104: Material | C104: 45930.025 | D104: 51430.627 | E104: 54730.988 | F104: 60506.62 | G104: 75358.245 | H104: 148516.25
B105: Installation | C105: 59470.717 | D105: 66592.958 | E105: 70866.303 | F105: 78344.657 | G105: 97574.709 | H105: 192300.52
B106: Hardware | C106: 19341.806 | D106: 22566.645 | E106: 24178.462 | F106: 27402.097 | G106: 32237.548 | H106: 79289.841
B107: Foundation | C107: 25077.129 | D107: 29930.65 | E107: 40446.01 | F107: 47726.895 | G107: 59860.095 | H107: 110822.67
...

Sheet Exploratory cost estimate
A1: MISO
A2: Cost Estimation Guide / Workbook for MTEP25
A3: Exploratory Cost Estimate (2025 dollars)
A4: This is not a Planning or Scoping level estimate
A5: XX/XX/2025
A7: Input cells-teal color
B9: Line | D9: Amounts include overhead, 30% contingency, 7.5% AFUDC
A10: State: | B10: Illinois | D10: Enter via drop down list
A11: Line type: | B11: A/C | D11: Enter via drop down list
A12: New / Rebuild / Reconductor: | B12: New | D12: Enter via drop down list
A13: Circuit: | B13: Single | D13: Enter via drop down list
A14: Voltage class: | B14: 345 kV | D14: Enter via drop down list
A15: Line length (miles): | B15: 100 | D15: Enter number of miles - recommend 30% adder to the straight line distance for exploratory estimate
A16: Total Capital Cost | B16: =IFERROR(INDEX('Exploratory cost data'!G2:R91,MATCH(CONCATENATE(B10,B11,B12,B13),'Exploratory cost data'!E2:E91,0),MATCH('Exploratory cost estimate'!B14,'Exploratory cost data'!G1:R1,0))*B15,"0") -> 370.49868 | D16: MTEP25 Exploratory Line Total Capital Cost includes contingency (30%) and AFUDC (7.5%)
A18: Project Cost | B18: =B16*0.715564 -> 265.11552 | D18: If Wisconsin, includes 5% environmental fee
A19: Contingency | B19: =B18*0.3 -> 79.534655 | D19: =B19/B18 -> 0.3
A20: AFUDC | B20: =(B18+B19)*0.075 -> 25.848763 | D20: =B20/(B19+B18) -> 0.075
A21: Project Implementation Cost (2025$) | B21: =SUM(B18:B20) -> 370.49894
B24: Substation #1 | D24: Amounts include overhead, 30% contingency, 7.5% AFUDC
A25: Facility: | B25: New - 4 positions (ring bus) | D25: Enter via drop down list
A26: Voltage class: | B26: 230 kV | D26: Enter via drop down list
A27: Total Capital Cost | B27: =IFERROR(INDEX('Exploratory cost data'!$G$92:$R$111,MATCH('Exploratory cost estimate'!B25,'Exploratory cost data'!$D$92:$D$111,0),MATCH('Exploratory cost estimate'!B26,'Exploratory cost data'!$G$1:$R$1,0)),"0") -> 13.582808 | D27: MTEP25 Exploratory Line Total Capital Cost includes contingency (30%) and AFUDC (7.5%)
A29: Project Cost | B29: =B27*0.715564 -> 9.7193683
A30: Contingency | B30: =B29*0.3 -> 2.9158105 | D30: =B30/B29 -> 0.3
A31: AFUDC | B31: =(B29+B30)*0.075 -> 0.94763841 | D31: =B31/(B30+B29) -> 0.075
A32: Total Capital Cost | B32: =SUM(B29:B31) -> 13.582817
B35: Substation #2 | D35: Amounts include overhead, 30% contingency, 7.5% AFUDC
A36: Facility: | B36: Upgrade - Add one position (breaker-and-a-half bus) | D36: Enter via drop down list
A37: Voltage class: | B37: 161 kV | D37: Enter via drop down list
A38: Total Capital Cost | B38: =IFERROR(INDEX('Exploratory cost data'!$G$92:$R$111,MATCH('Exploratory cost estimate'!B36,'Exploratory cost data'!$D$92:$D$111,0),MATCH('Exploratory cost estimate'!B37,'Exploratory cost data'!$G$1:$R$1,0)),"0") -> 2.6594878 | D38: MTEP25 Exploratory Line Total Capital Cost includes contingency (30%) and AFUDC (7.5%)
A40: Project Cost | B40: =B38*0.715564 -> 1.9030337
A41: Contingency | B41: =B40*0.3 -> 0.57091011 | D41: =B41/B40 -> 0.3
A42: AFUDC | B42: =(B40+B41)*0.075 -> 0.18554579 | D42: =B42/(B41+B40) -> 0.075
A43: Total Capital Cost | B43: =SUM(B40:B42) -> 2.6594896
B46: Add Transformer (breakers included)
A47: Primary voltage class: | B47: 345 kV | D47: Enter via drop down list
A48: Secondary voltage class: | B48: 161 kV | D48: Enter via drop down list
A49: Transformer MVA: | B49: 400 | D49: Enter MVA top rating (only type the number, the cell format will add the MVA)
A50: Total Capital Cost | B50: =IFERROR(B49*INDEX('Exploratory cost data'!$F$92:$S$124,MATCH('Exploratory cost estimate'!B47,'Exploratory cost data'!$E$92:$E$124,0),MATCH('Exploratory cost estimate'!B48,'Exploratory cost data'!$F$1:$S$1,0))/1000000+ HLOOKUP(B47,'Exploratory cost data'!$G$1:$N$112,112,FALSE())+ HLOOKUP(B48,'Exploratory cost data'!$G$1:$N$112,112,FALSE()),"0") -> 12.611199 | D50: MTEP25 Exploratory Line Total Capital Cost includes contingency (30%) and AFUDC (7.5%)
A52: Project Cost | B52: =B50*0.715564 -> 9.0241203
A53: Contingency | B53: =B52*0.3 -> 2.7072361 | D53: =B53/B52 -> 0.3
A54: AFUDC | B54: =(B52+B53)*0.075 -> 0.87985173 | D54: =B54/(B53+B52) -> 0.075
A55: Total Capital Cost | B55: =SUM(B52:B54) -> 12.611208
B60: Grand Total
A61: Project Cost from above | B61: =(B18+B29+B40+B52)*1000000 -> 2.8576204e+08
A62: Market uncertainty cost adder % | B62: =D62*B61 -> 28576204 | D62: 0.1 | E62: Market uncertainty cost adder %
A63: Additional Cost not included above | B63: 2000
A64: Additional Cost not included above | B64: 3000
A65: Additional Cost not included above | B65: 4000
A66: Project Cost Subtotal | B66: =SUM(B61:B65) -> 3.1434724e+08
A67: Contingency | B67: =B66*D67 -> 94304173 | D67: 0.3
A68: AFUDC | B68: =SUM(B66:B67)*D68 -> 30648856 | D68: 0.075
A69: Total Capital Cost | B69: =SUM(B66:B68) -> 4.3930027e+08
B76: =IFERROR(B49*INDEX('Exploratory cost data'!$F$92:$R$124,MATCH('Exploratory cost estimate'!B47,'Exploratory cost data'!$E$92:$E$124,0),MATCH('Exploratory cost estimate'!B48,'Exploratory cost data'!$F$1:$R$1,0))/1000000,"0") -> 4.8076694 | E76: 4807669.4 | F76: ='Exploratory cost data'!J118 -> 12019.173
F77: 400
B78: =IFERROR(HLOOKUP(B47,'Exploratory cost data'!$G$1:$N$112,112,FALSE()),"0") -> 5.1440423 | F78: =F76*F77 -> 4807669.4
B80: =IFERROR(HLOOKUP(B48,'Exploratory cost data'!$G$1:$N$112,112,FALSE()),"0") -> 2.6594878

Sheet Line Exploratory example
F1: Illinois
E2: Line Type: | F2: A/C
E3: Voltage class: | F3: 345 kV
E4: Facility type (Circuit): | F4: Single
E5: Structure type: | F5: Steel Pole
E6: Line length (miles): | F6: 1
E7: Conductor: | F7: 795 "Drake"
E8: Conductor type: | F8: ACSS
E9: Conductors per phase: | F9: 2
E10: Shieldwire quantity: | F10: 1
E11: OPGW quantity: | F11: 1
A14: Right-of-Way, land acquisition, and regulatory and permitting
B15: ROW width in feet | C15: Allocation % | D15: Unit / Acres | E15: Unit Cost
A16: Pasture land | B16: 175 | C16: 0.25 | D16: =B16*5280*$F$6*C16/43560 -> 5.3030303 | E16: 22032.86 | F16: =D16*E16 -> 116840.93
A17: Crop land | B17: 175 | C17: 0.65 | D17: =B17*5280*$F$6*C17/43560 -> 13.787879 | E17: 30290.46 | F17: =D17*E17 -> 417641.2
A18: Suburban/urban land | B18: 175 | C18: 0.1 | D18: =B18*5280*$F$6*C18/43560 -> 2.1212121 | E18: 38548.06 | F18: =D18*E18 -> 81768.613
F19: =SUM(F16:F18) -> 616250.74
A22: Structure material | F22: Cost per Pound
A23: Structures | B23: Units per Mile | C23: Number of Structures | D23: Steel Weights (lbs.) | E23: Total Steel Pounds | F23: 2.7503009
A24: Tangent | B24: 4.5 | C24: 4.5 | D24: 22300 | E24: =C24*D24 -> 100350 | F24: =E24*F$23 -> 275992.7
A25: Running angle | B25: 1 | C25: 1 | D25: 37900 | E25: =C25*D25 -> 37900 | F25: =E25*F$23 -> 104236.4
A26: Non-angled deadend | B26: 0.25 | C26: 0.25 | D26: 42400 | E26: =C26*D26 -> 10600 | F26: =E26*F$23 -> 29153.19
A27: Angled deadend | B27: 0.25 | C27: 0.25 | D27: 48100 | E27: =C27*D27 -> 12025 | F27: =E27*F$23 -> 33072.368
F28: =SUM(F24:F27) -> 442454.66
A31: Structure foundation | F31: Cost per Cu. Yd.
A32: Structures | B32: Foundation size (Cu. Yd) | C32: Number of Foundations | D32: Total Cubic Yards | F32: 1617.8404
A33: Tangent | B33: 21 | C33: 4.5 | D33: =B33*C33 -> 94.5 | F33: =D33*F$32 -> 152885.92
A34: Running angle | B34: 30 | C34: 1 | D34: =B34*C34 -> 30 | F34: =D34*F$32 -> 48535.213
A35: Non-angled deadend | B35: 33.5 | C35: 0.25 | D35: =B35*C35 -> 8.375 | F35: =D35*F$32 -> 13549.413
A36: Angled deadend | B36: 41.5 | C36: 0.25 | D36: =B36*C36 -> 10.375 | F36: =D36*F$32 -> 16785.094
F37: =SUM(F33:F36) -> 231755.64
A40: Structure Hardware / Insulators / Grounding - "Hardware" data
A41: Structures | C41: Number of Structures | D41: Cost per Unit
A42: Tangent | C42: 4.5 | D42: 11091.181 | F42: =C42*D42 -> 49910.317
A43: Running angle | C43: 1 | D43: 11091.181 | F43: =C43*D43 -> 11091.181
A44: Non-angled deadend | C44: 0.25 | D44: 39865.371 | F44: =C44*D44 -> 9966.3427
A45: Angled deadend | C45: 0.25 | D45: 39865.371 | F45: =C45*D45 -> 9966.3427
E46: Total Structure and conductor accessories | F46: =SUM(F42:F45) -> 80934.184
A49: Structure construction labor "Installation data"
A50: Structures | B50: Unit of Measure | C50: Number of Units | D50: Cost per Unit
A51: Tangent | B51: Each | C51: 4.5 | D51: 79412.993 | F51: =C51*D51 -> 357358.47
A52: Running angle | B52: Each | C52: 1 | D52: 134966.48 | F52: =C52*D52 -> 134966.48
A53: Non-angled deadend | B53: Each | C53: 0.25 | D53: 150991.52 | F53: =C53*D53 -> 37747.88
A54: Angled deadend | B54: Each | C54: 0.25 | D54: 171289.91 | F54: =C54*D54 -> 42822.477
C55: =SUM(C51:C54) -> 6
A57: Forested | B57: Right-of-way width in feet | C57: 175
A58: Forested | B58: Percentage | C58: 0.4
A59: Project length | B59: Miles | C59: 1
A60: Forested clearing | B60: ACRE | C60: =(C57*5280)*(C59/43560)*C58 -> 8.4848485 | D60: 5485.8217 | F60: =C60*D60 -> 46546.366
A62: Wetland | B62: Right-of-way width in feet | C62: 175
A63: Wetland | B63: Wetland percentage | C63: 0.05
A64: Project length | B64: Miles | C64: 1
A65: Wetland matting & construction | B65: ACRE | C65: =(C62*5280)*(C64/43560)*C63 -> 1.0606061 | D65: 64027.043 | F65: =C65*D65 -> 67907.47
A66: Wetland mitigation credits | B66: ACRE | C66: =C65 -> 1.0606061 | D66: 51360.688 | F66: =C66*D66 -> 54473.457
A67: Mountainous | B67: ACRE | D67: 7131.7802 | F67: =C67*D67 -> 0
F68: =SUM(F51:F67) -> 741822.59
A71: Conductor "Materials" data plus "Accessories" data
D72: Conductor Material | E72: $ per Phase
D73: Conductor (Type / Phase) | E73: ACSS 795 "Drake" | F73: 1951.5901
D74: Conductors per phase: | F74: =F9 -> 2
D75: Facility type (Circuit): | E75: =$F$4 -> Single | F75: =IF($E$75="Single",1,2) -> 1
D76: Line length (miles): | F76: 1
E77: Wastage, Sag, Clipping | F77: 1.04
E78: Feet to Mile calculation | F78: 5.28
E79: Conductor phases | F79: 3
E80: Sub-total | F80: =F73*F74*F75*F76*F77*F78*F79 -> 64299.429
D81: Conductor Accessories | E81: $ per Phase
D82: Conductor (Type / Phase) | E82: ACSS 795 "Drake" | F82: 298.7651
D83: Conductors per phase: | F83: 2
D84: Facility type (Circuit): | E84: =$F$4 -> Single | F84: =IF($E$84="Single",1,2) -> 1
D85: Line length (miles): | F85: 1
E86: Wastage, Sag, Clipping | F86: 1.04
E87: Feet to Mile calculation | F87: 5.28
E88: Conductor phases | F88: 3
E89: Sub-total | F89: =F82*F83*F84*F85*F86*F87*F88 -> 9843.4736
E90: Total Conductor materials and accessories | F90: =F80+F89 -> 74142.902
A93: Conductor Construction Labor "Installation data"
D94: Conductor Material | E94: $ per Phase
D95: Conductor (Type / Phase) | E95: ACSS 795 "Drake" | F95: 4558.1268
D96: Conductors per phase: | F96: 2
D97: Facility type (Circuit): | E97: =$F$4 -> Single | F97: =IF($E$97="Single",1,2) -> 1
D98: Line length (miles): | F98: 1
E99: Sag, clip, waste factor | F99: 1.04
E100: Mile to feet | F100: 5.28
E101: 3 Phase | F101: 3
F102: =F95*F96*F97*F98*F99*F100*F101 -> 150177.52
A105: OPGW and /or Shieldwire "Material data"
C106: Conductor Material | D106: Quantity | E106: $ per 1,000 feet
C107: Shieldwire | D107: 1 | E107: 673.0268 | F107: =D107*E107 -> 673.0268
C108: OPGW | D108: 1 | E108: 3044.8833 | F108: =D108*E108 -> 3044.8833
C109: Total cost per 1,000 feet | F109: =F107+F108 -> 3717.9101
E110: Line length (miles): | F110: 1
E111: Sag, clip, waste factor | F111: 1.04
E112: Mile to feet | F112: 5.28
F113: =F109*F110*F111*F112 -> 20415.788
A116: OPGW and /or Shieldwire "Installation data"
C117: Conductor Material | D117: Quantity | E117: $ per 1,000 feet
C118: Shieldwire | D118: 1 | E118: 1722.0887 | F118: =D118*E118 -> 1722.0887
C119: OPGW | D119: 1 | E119: 7781.3685 | F119: =D119*E119 -> 7781.3685
C120: Total cost per 1,000 feet | F120: =F118+F119 -> 9503.4572
...

Sheet Substation Explor. example 
E1: State: | F1: Illinois
E2: Facility type and scope of work: | F2: New site - 4 positions (double-breaker bus)
E3: Voltage class: | F3: 345 kV
E4: Land Type: | F4: Suburban/urban land
E5: Terrain Type: | F5: Wetland
E6: Electrical equipment material - Power transformer (MVA)
E7: Electrical equipment material - Bus or Transformer secondary voltage | F7: 345 kV
E8: Electrical equipment material - (MVAr) type
E9: Electrical equipment material - (MVAr) size
D11: acres | E11: Land required | F11: 9
D12: miles | E12: Access road | F12: 1
D13: each | E13: Circuit breaker | F13: 8
D14: each | E14: Disconnect switch | F14: 16
D15: set of 3 | E15: Voltage transformer | F15: 6
D16: 3-phase | E16: Bus support, bus, and fittings | F16: 20
D17: each | E17: Deadend structure | F17: 4
D18: each | E18: Control enclosure | F18: 1
D19: each | E19: Relay panel | F19: 10
D20: feet | E20: Control cable | F20: 48000
D21: feet | E21: Conduit | F21: 4800
D22: per foot | E22: Cable trench | F22: 480
A25: Land acquisition, and regulatory and permitting
A26: State | B26: Land & Terrain Type | C26: Acres | D26: Cost per acre
A27: Illinois | B27: Suburban/urban land | C27: 9 | D27: 38548.06 | F27: =C27*D27 -> 346932.54
F28: =F27 -> 346932.54
A30: Site work
B31: Terrain Type | C31: Acres | D31: Cost per acre
A32: Site work | B32: Applies to all types | C32: 9 | D32: 419680.81 | F32: =C32*D32 -> 3777127.3
B33: Wetland | C33: 9 | D33: 64027.043 | F33: =C33*D33 -> 576243.39
B34: Wetland mitigation credits | C34: 9 | D34: 51360.688 | F34: =C34*D34 -> 462246.19
F35: =SUM(F32:F34) -> 4815616.9
A37: Access Road
A38: Access road | D38: Unit Cost per mile | E38: 648250.47 | F38: =E38 -> 648250.47
A40: Steel support structure material
F41: Cost per Pound
A42: Structures | B42: Units | C42: Number of units | D42: Steel stand weight | E42: Total Steel Pounds | F42: 2.7503009
A43: Disconnect switch | B43: each | C43: 16 | D43: 4000 | E43: =C43*D43 -> 64000 | F43: =E43*F$42 -> 176019.26
A44: Voltage transformer | B44: set of 3 | C44: 6 | D44: 2000 | E44: =C44*D44 -> 12000 | F44: =E44*F$42 -> 33003.611
A45: Bus support, bus, and fittings | B45: 3-phase | C45: 20 | D45: 3000 | E45: =C45*D45 -> 60000 | F45: =E45*F$42 -> 165018.05
A46: Deadend structure | B46: each | C46: 4 | D46: 48100 | E46: =C46*D46 -> 192400 | F46: =E46*F$42 -> 529157.9
E47: Total Structure Material | F47: =SUM(F43:F46) -> 903198.82
A49: Steel support structure installation
A50: Structures | B50: Units | C50: Number of units | D50: Steel stand installation
A51: Disconnect switch | B51: each | C51: 16 | D51: 12456.046 | F51: =C51*D51 -> 199296.74
A52: Voltage transformer | B52: set of 3 | C52: 6 | D52: 6206.3394 | F52: =C52*D52 -> 37238.036
A53: Bus support, bus, and fittings | B53: 3-phase | C53: 20 | D53: 9309.5091 | F53: =C53*D53 -> 186190.18
A54: Deadend structure | B54: each | C54: 4 | D54: 171289.91 | F54: =C54*D54 -> 685159.63
F55: =SUM(F51:F54) -> 1107884.6
A57: Substation foundations
F58: Cost per Cu. Yd.
A59: Structures | B59: Units | C59: Number of Structures | D59: Foundation size Cu. Yd. | E59: Total Cubic Yards | F59: 1617.8404
A60: Circuit breaker | B60: Circuit breaker | C60: 8 | D60: 8.8 | E60: =C60*D60 -> 70.4 | F60: =E60*F$59 -> 113895.97
A61: Disconnect switch | B61: Disconnect switch | C61: 16 | D61: 8 | E61: =C61*D61 -> 128 | F61: =E61*F$59 -> 207083.57
A62: Voltage transformer | B62: Voltage transformer | C62: 6 | D62: 8 | E62: =C62*D62 -> 48 | F62: =E62*F$59 -> 77656.34
A63: Bus support, bus, and fittings | B63: Bus support, bus, and fittings | C63: 20 | D63: 9.6 | E63: =C63*D63 -> 192 | F63: =E63*F$59 -> 310625.36
A64: Deadend structure | B64: Deadend structure | C64: 4 | D64: 41.5 | E64: =C64*D64 -> 166 | F64: =E64*F$59 -> 268561.51
A65: Control Enclosure | B65: Control enclosure | C65: 1 | D65: 36 | E65: =C65*D65 -> 36 | F65: =E65*F$59 -> 58242.255
F66: =SUM(F60:F65) -> 1036065
A68: Electrical equipment material
A69: Structures | B69: Unit of Measure | C69: Number of Units | D69: Material | E69: Jumpers, conduit, wiring, grounding
A70: Circuit breaker | B70: each | C70: 8 | D70: 403269.4 | E70: 24695.256 | F70: =C70*(D70+E70) -> 3423717.3
A71: Disconnect switch | B71: each | C71: 16 | D71: 44878.878 | E71: 12347.628 | F71: =C71*(D71+E71) -> 915624.1
A72: Voltage transformer | B72: set of 3 | C72: 6 | D72: 53854.654 | E72: 18521.442 | F72: =C72*(D72+E72) -> 434256.58
A73: Bus support, bus, and fittings | B73: 3-phase | C73: 20 | D73: 13880.865 | E73: 0 | F73: =C73*(D73+E73) -> 277617.3
A74: Power transformer | B74: MVA | C74: 0 | D74: 0 | F74: =C74*(D74+E74) -> 0
A75: MVAr Equipment | B75: MVAr | C75: 0 | D75: 0 | F75: =C75*(D75+E75) -> 0
F76: =SUM(F70:F75) -> 5051215.3
A78: Electrical equipment installation
A79: Structures | B79: Unit of Measure | C79: Number of Units | D79: Installation
A80: Circuit breaker | B80: each | C80: 8 | D80: 18521.442 | F80: =C80*D80 -> 148171.53
A81: Disconnect switch | B81: each | C81: 16 | D81: 18521.442 | F81: =C81*D81 -> 296343.07
A82: Voltage transformer | B82: set of 3 | C82: 6 | D82: 4939.0512 | F82: =C82*D82 -> 29634.307
A83: Bus support, bus, and fittings | B83: 3-phase | C83: 20 | D83: 16039.87 | F83: =C83*D83 -> 320797.4
A84: Hardware/Insulators/Grounding | C84: 4 | D84: 39865.371 | F84: =C84*D84 -> 159461.48
F85: =SUM(F80:F84) -> 954407.79
A87: Control enclosure - not including communication equipment
A88: Structures | C88: Number of Units | D88: All except comm. equip.
A89: Control enclosure | B89: each | C89: 1 | D89: 1391786.1 | F89: =C89*D89 -> 1391786.1
A91: Relay panels
A92: Structures | C92: Number of Units | D92: Material | E92: Installation
A93: Relay panel | B93: each | C93: 10 | D93: 60194.987 | E93: 120389.97 | F93: =C93*(D93+E93) -> 1805849.6
A95: Communication system
A96: Structures | C96: Number of Units | D96: Communication equipment
A97: Control enclosure | B97: each | C97: 1 | D97: 185214.42 | F97: =C97*D97 -> 185214.42
A99: Control cable, conduit, and cable trench
A100: Structures | C100: Number of Units | D100: Material | E100: Installation
A101: Control cable | B101: feet | C101: 48000 | D101: 4.9390512 | E101: 6.173814 | F101: =C101*(D101+E101) -> 533417.53
A102: Conduit | B102: feet | C102: 4800 | D102: 3.7042884 | E102: 49.390512 | F102: =C102*(D102+E102) -> 254855.04
A103: Cable trench | B103: per foot | C103: 480 | D103: 61.436978 | E103: 246.95256 | F103: =C103*(D103+E103) -> 148026.98
F104: =SUM(F101:F103) -> 936299.54
D107: Project management | E107: 0.055 | F107: =SUM(F$110:F$121)*E107 -> 1055049.7
D108: Engineering, environmental studies, and testing and commissioning | E108: 0.03 | F108: =SUM(F$110:F$121)*E108 -> 575481.63
D109: Administrative & General overhead (A&G) | E109: 0.015 | F109: =SUM(F$110:F$121)*E109 -> 287740.82
D110: Land acquisition, and regulatory and permitting | F110: =F28 -> 346932.54
D111: Site work | F111: =F35 -> 4815616.9
D112: Access roads | F112: =F38 -> 648250.47
D113: Steel support structure material | F113: =F47 -> 903198.82
D114: Steel support structure construction labor | F114: =F55 -> 1107884.6
D115: Substations foundations | F115: =F66 -> 1036065
D116: Electrical equipment material | F116: =F76 -> 5051215.3
...

Sheet Exploratory cost data
A1: State | B1: Line Type | C1: Type | D1: Circuit | E1: Concatenate | F1: N/A | G1: 69 kV | H1: 115 kV | I1: 138 kV | J1: 161 kV | K1: 230 kV | L1: 345 kV | M1: 500 kV | N1: 765 kV | O1: ± 250 kV | P1: ± 400 kV | Q1: ± 500 kV | R1: ± 600 kV | S1: ± 640 kV
A2: Arkansas | B2: A/C | C2: New | D2: Single | E2: ArkansasA/CNewSingle | G2: 1.8192286 | H2: 2.0215667 | I2: 2.114778 | J2: 2.1558346 | K2: 2.2992153 | L2: 3.6677244 | M2: 4.6493896 | N2: 5.879689
A3: Illinois | B3: A/C | C3: New | D3: Single | E3: IllinoisA/CNewSingle | G3: 1.8362628 | H3: 2.0407302 | I3: 2.1350062 | J3: 2.1771274 | K3: 2.3258313 | L3: 3.7049868 | M3: 4.6919752 | N3: 5.9275978
A4: Indiana | B4: A/C | C4: New | D4: Single | E4: IndianaA/CNewSingle | G4: 1.7614037 | H4: 1.9565137 | I4: 2.046111 | J4: 2.0835535 | K4: 2.2088639 | L4: 3.5412325 | M4: 4.5048274 | N4: 5.7170565
A5: Iowa | B5: A/C | C5: New | D5: Single | E5: IowaA/CNewSingle | G5: 1.8124239 | H5: 2.0139114 | I5: 2.1066974 | J5: 2.1473287 | K5: 2.2885829 | L5: 3.6528391 | M5: 4.6323778 | N5: 5.8605507
A6: Kentucky | B6: A/C | C6: New | D6: Single | E6: KentuckyA/CNewSingle | G6: 1.9016273 | H6: 2.1142652 | I6: 2.2126265 | J6: 2.2588329 | K6: 2.4279633 | L6: 3.8479715 | M6: 4.8553863 | N6: 6.1114353
A7: Louisiana | B7: A/C | C7: New | D7: Single | E7: LouisianaA/CNewSingle | G7: 2.0564702 | H7: 2.2884635 | I7: 2.3965024 | J7: 2.4523865 | K7: 2.6699053 | L7: 4.1866904 | M7: 5.2424936 | N7: 6.5469309
A8: Michigan | B8: A/C | C8: New | D8: Single | E8: MichiganA/CNewSingle | G8: 1.8804072 | H8: 2.0903927 | I8: 2.1874277 | J8: 2.2323079 | K8: 2.394807 | L8: 3.8015527 | M8: 4.8023362 | N8: 6.0517539
A9: Minnesota | B9: A/C | C9: New | D9: Single | E9: MinnesotaA/CNewSingle | G9: 1.8682813 | H9: 2.076751 | I9: 2.1730281 | J9: 2.2171505 | K9: 2.3758602 | L9: 3.7750272 | M9: 4.7720214 | N9: 6.0176497
A10: Mississippi | B10: A/C | C10: New | D10: Single | E10: MississippiA/CNewSingle | G10: 2.0464243 | H10: 2.2771618 | I10: 2.3845729 | J10: 2.4398292 | K10: 2.6542086 | L10: 4.1647149 | M10: 5.2173788 | N10: 6.5186768
A11: Missouri | B11: A/C | C11: New | D11: Single | E11: MissouriA/CNewSingle | G11: 1.7932767 | H11: 1.9923708 | I11: 2.0839601 | J11: 2.1233947 | K11: 2.2586655 | L11: 3.6109546 | M11: 4.5845098 | N11: 5.8066992
A12: Montana | B12: A/C | C12: New | D12: Single | E12: MontanaA/CNewSingle | G12: 1.67039 | H12: 1.8541233 | I12: 1.9380322 | J12: 1.9697863 | K12: 2.066655 | L12: 3.34214 | M12: 4.2772931 | N12: 5.4610804
A13: North Dakota | B13: A/C | C13: New | D13: Single | E13: North DakotaA/CNewSingle | G13: 1.7015965 | H13: 1.8892305 | I13: 1.9750899 | J13: 2.0087944 | K13: 2.1154151 | L13: 3.4104041 | M13: 4.3553093 | N13: 5.5488486
... A16: Wisconsin | B16: A/C | C16: New | D16: Single | E16: WisconsinA/CNewSingle | G16: 1.9877884 | H16: 2.2100306 | I16: 2.3128239 | J16: 2.3610365 | K16: 2.5373188 | L16: 4.0219447 | M16: 5.0755014 | N16: 6.3892567
A17: Arkansas | B17: A/C | C17: New | D17: Double | E17: ArkansasA/CNewDouble | G17: 2.5915586 | H17: 2.9259936 | I17: 3.092929 | J17: 3.1682791 | K17: 3.7202569 | L17: 6.0991714 | M17: N/A | N17: N/A
A18: Illinois | B18: A/C | C18: New | D18: Double | E18: IllinoisA/CNewDouble | G18: 2.6085928 | H18: 2.9451572 | I18: 3.1131572 | J18: 3.1895719 | K18: 3.7468729 | L18: 6.1364338 | M18: N/A | N18: N/A
A19: Indiana | B19: A/C | C19: New | D19: Double | E19: IndianaA/CNewDouble | G19: 2.5337337 | H19: 2.8609406 | I19: 3.024262 | J19: 3.095998 | K19: 3.6299056 | L19: 5.9726795 | M19: N/A | N19: N/A
A20: Iowa | B20: A/C | C20: New | D20: Double | E20: IowaA/CNewDouble | G20: 2.5847538 | H20: 2.9183383 | I20: 3.0848484 | J20: 3.1597732 | K20: 3.7096246 | L20: 6.084286 | M20: N/A | N20: N/A
A21: Kentucky | B21: A/C | C21: New | D21: Double | E21: KentuckyA/CNewDouble | G21: 2.6739573 | H21: 3.0186922 | I21: 3.1907774 | J21: 3.2712774 | K21: 3.8490049 | L21: 6.2794185 | M21: N/A | N21: N/A
A22: Louisiana | B22: A/C | C22: New | D22: Double | E22: LouisianaA/CNewDouble | G22: 2.8288002 | H22: 3.1928904 | I22: 3.3746534 | J22: 3.464831 | K22: 4.0909469 | L22: 6.6181373 | M22: N/A | N22: N/A
A23: Michigan | B23: A/C | C23: New | D23: Double | E23: MichiganA/CNewDouble | G23: 2.6527372 | H23: 2.9948196 | I23: 3.1655787 | J23: 3.2447524 | K23: 3.8158486 | L23: 6.2329997 | M23: N/A | N23: N/A
A24: Minnesota | B24: A/C | C24: New | D24: Double | E24: MinnesotaA/CNewDouble | G24: 2.6406113 | H24: 2.9811779 | I24: 3.1511791 | J24: 3.2295949 | K24: 3.7969018 | L24: 6.2064742 | M24: N/A | N24: N/A
A25: Mississippi | B25: A/C | C25: New | D25: Double | E25: MississippiA/CNewDouble | G25: 2.8187543 | H25: 3.1815888 | I25: 3.3627239 | J25: 3.4522737 | K25: 4.0752502 | L25: 6.5961619 | M25: N/A | N25: N/A
A26: Missouri | B26: A/C | C26: New | D26: Double | E26: MissouriA/CNewDouble | G26: 2.5656067 | H26: 2.8967977 | I26: 3.0621111 | J26: 3.1358392 | K26: 3.6797071 | L26: 6.0424016 | M26: N/A | N26: N/A
A27: Montana | B27: A/C | C27: New | D27: Double | E27: MontanaA/CNewDouble | G27: 2.44272 | H27: 2.7585502 | I27: 2.9161832 | J27: 2.9822308 | K27: 3.4876966 | L27: 5.773587 | M27: N/A | N27: N/A
A28: North Dakota | B28: A/C | C28: New | D28: Double | E28: North DakotaA/CNewDouble | G28: 2.4739264 | H28: 2.7936575 | I28: 2.9532408 | J28: 3.0212389 | K28: 3.5364567 | L28: 5.8418511 | M28: N/A | N28: N/A
... A31: Wisconsin | B31: A/C | C31: New | D31: Double | E31: WisconsinA/CNewDouble | G31: 2.6717722 | H31: 3.0162339 | I31: 3.1881827 | J31: 3.2685461 | K31: 3.8455907 | L31: 6.2746386 | M31: N/A | N31: N/A
A32: Arkansas | B32: A/C | C32: Rebuild | D32: Single | E32: ArkansasA/CRebuildSingle | G32: 1.5978841 | H32: 1.7724764 | I32: 1.8517902 | J32: 1.8787874 | K32: 1.9516798 | L32: N/A | M32: N/A | N32: N/A
A33: Illinois | B33: A/C | C33: Rebuild | D33: Single | E33: IllinoisA/CRebuildSingle | G33: 1.5978841 | H33: 1.7724764 | I33: 1.8517902 | J33: 1.8787874 | K33: 1.9516798 | L33: N/A | M33: N/A | N33: N/A
A34: Indiana | B34: A/C | C34: Rebuild | D34: Single | E34: IndianaA/CRebuildSingle | G34: 1.5978841 | H34: 1.7724764 | I34: 1.8517902 | J34: 1.8787874 | K34: 1.9516798 | L34: N/A | M34: N/A | N34: N/A
A35: Iowa | B35: A/C | C35: Rebuild | D35: Single | E35: IowaA/CRebuildSingle | G35: 1.5978841 | H35: 1.7724764 | I35: 1.8517902 | J35: 1.8787874 | K35: 1.9516798 | L35: N/A | M35: N/A | N35: N/A
A36: Kentucky | B36: A/C | C36: Rebuild | D36: Single | E36: KentuckyA/CRebuildSingle | G36: 1.5978841 | H36: 1.7724764 | I36: 1.8517902 | J36: 1.8787874 | K36: 1.9516798 | L36: N/A | M36: N/A | N36: N/A
A37: Louisiana | B37: A/C | C37: Rebuild | D37: Single | E37: LouisianaA/CRebuildSingle | G37: 1.5978841 | H37: 1.7724764 | I37: 1.8517902 | J37: 1.8787874 | K37: 1.9516798 | L37: N/A | M37: N/A | N37: N/A
A38: Michigan | B38: A/C | C38: Rebuild | D38: Single | E38: MichiganA/CRebuildSingle | G38: 1.5978841 | H38: 1.7724764 | I38: 1.8517902 | J38: 1.8787874 | K38: 1.9516798 | L38: N/A | M38: N/A | N38: N/A
A39: Minnesota | B39: A/C | C39: Rebuild | D39: Single | E39: MinnesotaA/CRebuildSingle | G39: 1.5978841 | H39: 1.7724764 | I39: 1.8517902 | J39: 1.8787874 | K39: 1.9516798 | L39: N/A | M39: N/A | N39: N/A
A40: Mississippi | B40: A/C | C40: Rebuild | D40: Single | E40: MississippiA/CRebuildSingle | G40: 1.5978841 | H40: 1.7724764 | I40: 1.8517902 | J40: 1.8787874 | K40: 1.9516798 | L40: N/A | M40: N/A | N40: N/A
A41: Missouri | B41: A/C | C41: Rebuild | D41: Single | E41: MissouriA/CRebuildSingle | G41: 1.5978841 | H41: 1.7724764 | I41: 1.8517902 | J41: 1.8787874 | K41: 1.9516798 | L41: N/A | M41: N/A | N41: N/A
A42: Montana | B42: A/C | C42: Rebuild | D42: Single | E42: MontanaA/CRebuildSingle | G42: 1.5978841 | H42: 1.7724764 | I42: 1.8517902 | J42: 1.8787874 | K42: 1.9516798 | L42: N/A | M42: N/A | N42: N/A
A43: North Dakota | B43: A/C | C43: Rebuild | D43: Single | E43: North DakotaA/CRebuildSingle | G43: 1.5978841 | H43: 1.7724764 | I43: 1.8517902 | J43: 1.8787874 | K43: 1.9516798 | L43: N/A | M43: N/A | N43: N/A
... A46: Wisconsin | B46: A/C | C46: Rebuild | D46: Single | E46: WisconsinA/CRebuildSingle | G46: 1.5978841 | H46: 1.7724764 | I46: 1.8517902 | J46: 1.8787874 | K46: 1.9516798 | L46: N/A | M46: N/A | N46: N/A
A47: Arkansas | B47: A/C | C47: Rebuild | D47: Double | E47: ArkansasA/CRebuildDouble | G47: 2.3643243 | H47: 2.6703551 | I47: N/A | J47: N/A | K47: N/A | L47: N/A | M47: N/A | N47: N/A
A48: Illinois | B48: A/C | C48: Rebuild | D48: Double | E48: IllinoisA/CRebuildDouble | G48: 2.3643243 | H48: 2.6703551 | I48: N/A | J48: N/A | K48: N/A | L48: N/A | M48: N/A | N48: N/A
A49: Indiana | B49: A/C | C49: Rebuild | D49: Double | E49: IndianaA/CRebuildDouble | G49: 2.3643243 | H49: 2.6703551 | I49: N/A | J49: N/A | K49: N/A | L49: N/A | M49: N/A | N49: N/A
A50: Iowa | B50: A/C | C50: Rebuild | D50: Double | E50: IowaA/CRebuildDouble | G50: 2.3643243 | H50: 2.6703551 | I50: N/A | J50: N/A | K50: N/A | L50: N/A | M50: N/A | N50: N/A
A51: Kentucky | B51: A/C | C51: Rebuild | D51: Double | E51: KentuckyA/CRebuildDouble | G51: 2.3643243 | H51: 2.6703551 | I51: N/A | J51: N/A | K51: N/A | L51: N/A | M51: N/A | N51: N/A
A52: Louisiana | B52: A/C | C52: Rebuild | D52: Double | E52: LouisianaA/CRebuildDouble | G52: 2.3643243 | H52: 2.6703551 | I52: N/A | J52: N/A | K52: N/A | L52: N/A | M52: N/A | N52: N/A
A53: Michigan | B53: A/C | C53: Rebuild | D53: Double | E53: MichiganA/CRebuildDouble | G53: 2.3643243 | H53: 2.6703551 | I53: N/A | J53: N/A | K53: N/A | L53: N/A | M53: N/A | N53: N/A
A54: Minnesota | B54: A/C | C54: Rebuild | D54: Double | E54: MinnesotaA/CRebuildDouble | G54: 2.3643243 | H54: 2.6703551 | I54: N/A | J54: N/A | K54: N/A | L54: N/A | M54: N/A | N54: N/A
A55: Mississippi | B55: A/C | C55: Rebuild | D55: Double | E55: MississippiA/CRebuildDouble | G55: 2.3643243 | H55: 2.6703551 | I55: N/A | J55: N/A | K55: N/A | L55: N/A | M55: N/A | N55: N/A
A56: Missouri | B56: A/C | C56: Rebuild | D56: Double | E56: MissouriA/CRebuildDouble | G56: 2.3643243 | H56: 2.6703551 | I56: N/A | J56: N/A | K56: N/A | L56: N/A | M56: N/A | N56: N/A
A57: Montana | B57: A/C | C57: Rebuild | D57: Double | E57: MontanaA/CRebuildDouble | G57: 2.3643243 | H57: 2.6703551 | I57: N/A | J57: N/A | K57: N/A | L57: N/A | M57: N/A | N57: N/A
A58: North Dakota | B58: A/C | C58: Rebuild | D58: Double | E58: North DakotaA/CRebuildDouble | G58: 2.3643243 | H58: 2.6703551 | I58: N/A | J58: N/A | K58: N/A | L58: N/A | M58: N/A | N58: N/A
... A61: Wisconsin | B61: A/C | C61: Rebuild | D61: Double | E61: WisconsinA/CRebuildDouble | G61: 2.3643243 | H61: 2.6703551 | I61: N/A | J61: N/A | K61: N/A | L61: N/A | M61: N/A | N61: N/A
A62: Arkansas | B62: A/C | C62: Reconductor | D62: Single | E62: ArkansasA/CReconductorSingle | G62: 0.40669507 | H62: 0.47593571 | I62: 0.47957864 | J62: 0.48190546 | K62: 0.48190546 | L62: 0.75699545 | M62: 1.0527869 | N62: 1.4570206
A63: Illinois | B63: A/C | C63: Reconductor | D63: Single | E63: IllinoisA/CReconductorSingle | G63: 0.40669507 | H63: 0.47593571 | I63: 0.47957864 | J63: 0.48190546 | K63: 0.48190546 | L63: 0.75699545 | M63: 1.0527869 | N63: 1.4570206
A64: Indiana | B64: A/C | C64: Reconductor | D64: Single | E64: IndianaA/CReconductorSingle | G64: 0.40669507 | H64: 0.47593571 | I64: 0.47957864 | J64: 0.48190546 | K64: 0.48190546 | L64: 0.75699545 | M64: 1.0527869 | N64: 1.4570206
A65: Iowa | B65: A/C | C65: Reconductor | D65: Single | E65: IowaA/CReconductorSingle | G65: 0.40669507 | H65: 0.47593571 | I65: 0.47957864 | J65: 0.48190546 | K65: 0.48190546 | L65: 0.75699545 | M65: 1.0527869 | N65: 1.4570206
A66: Kentucky | B66: A/C | C66: Reconductor | D66: Single | E66: KentuckyA/CReconductorSingle | G66: 0.40669507 | H66: 0.47593571 | I66: 0.47957864 | J66: 0.48190546 | K66: 0.48190546 | L66: 0.75699545 | M66: 1.0527869 | N66: 1.4570206
A67: Louisiana | B67: A/C | C67: Reconductor | D67: Single | E67: LouisianaA/CReconductorSingle | G67: 0.40669507 | H67: 0.47593571 | I67: 0.47957864 | J67: 0.48190546 | K67: 0.48190546 | L67: 0.75699545 | M67: 1.0527869 | N67: 1.4570206
A68: Michigan | B68: A/C | C68: Reconductor | D68: Single | E68: MichiganA/CReconductorSingle | G68: 0.40669507 | H68: 0.47593571 | I68: 0.47957864 | J68: 0.48190546 | K68: 0.48190546 | L68: 0.75699545 | M68: 1.0527869 | N68: 1.4570206
A69: Minnesota | B69: A/C | C69: Reconductor | D69: Single | E69: MinnesotaA/CReconductorSingle | G69: 0.40669507 | H69: 0.47593571 | I69: 0.47957864 | J69: 0.48190546 | K69: 0.48190546 | L69: 0.75699545 | M69: 1.0527869 | N69: 1.4570206
A70: Mississippi | B70: A/C | C70: Reconductor | D70: Single | E70: MississippiA/CReconductorSingle | G70: 0.40669507 | H70: 0.47593571 | I70: 0.47957864 | J70: 0.48190546 | K70: 0.48190546 | L70: 0.75699545 | M70: 1.0527869 | N70: 1.4570206
A71: Missouri | B71: A/C | C71: Reconductor | D71: Single | E71: MissouriA/CReconductorSingle | G71: 0.40669507 | H71: 0.47593571 | I71: 0.47957864 | J71: 0.48190546 | K71: 0.48190546 | L71: 0.75699545 | M71: 1.0527869 | N71: 1.4570206
A72: Montana | B72: A/C | C72: Reconductor | D72: Single | E72: MontanaA/CReconductorSingle | G72: 0.40669507 | H72: 0.47593571 | I72: 0.47957864 | J72: 0.48190546 | K72: 0.48190546 | L72: 0.75699545 | M72: 1.0527869 | N72: 1.4570206
A73: North Dakota | B73: A/C | C73: Reconductor | D73: Single | E73: North DakotaA/CReconductorSingle | G73: 0.40669507 | H73: 0.47593571 | I73: 0.47957864 | J73: 0.48190546 | K73: 0.48190546 | L73: 0.75699545 | M73: 1.0527869 | N73: 1.4570206
... A76: Wisconsin | B76: A/C | C76: Reconductor | D76: Single | E76: WisconsinA/CReconductorSingle | G76: 0.40669507 | H76: 0.47593571 | I76: 0.47957864 | J76: 0.48190546 | K76: 0.48190546 | L76: 0.75699545 | M76: 1.0527869 | N76: 1.4570206
A77: Arkansas | B77: HVDC | C77: New | D77: Single | E77: ArkansasHVDCNewSingle | O77: 2.4247723 | P77: 2.8726803 | Q77: 3.0173509 | R77: 3.2113838 | S77: 5.7606139
A78: Illinois | B78: HVDC | C78: New | D78: Single | E78: IllinoisHVDCNewSingle | O78: 2.4524529 | P78: 2.9110074 | Q78: 3.0599365 | R78: 3.2571633 | S78: 5.8085227
A79: Indiana | B79: HVDC | C79: New | D79: Single | E79: IndianaHVDCNewSingle | O79: 2.3308068 | P79: 2.7425743 | Q79: 2.8727887 | R79: 3.0559794 | S79: 5.5979814
A80: Iowa | B80: HVDC | C80: New | D80: Single | E80: IowaHVDCNewSingle | O80: 2.4137146 | P80: 2.8573697 | Q80: 3.0003391 | R80: 3.1930961 | S80: 5.7414756
A81: Kentucky | B81: HVDC | C81: New | D81: Single | E81: KentuckyHVDCNewSingle | O81: 2.5586701 | P81: 3.0580774 | Q81: 3.2233476 | R81: 3.4328302 | S81: 5.9923602
A82: Louisiana | B82: HVDC | C82: New | D82: Single | E82: LouisianaHVDCNewSingle | O82: 2.8102898 | P82: 3.4064739 | Q82: 3.6104549 | R82: 3.8489705 | S82: 6.4278558
A83: Michigan | B83: HVDC | C83: New | D83: Single | E83: MichiganHVDCNewSingle | O83: 2.5241876 | P83: 3.0103323 | Q83: 3.1702975 | R83: 3.3758014 | S83: 5.9326788
A84: Minnesota | B84: HVDC | C84: New | D84: Single | E84: MinnesotaHVDCNewSingle | O84: 2.5044829 | P84: 2.9830489 | Q84: 3.1399827 | R84: 3.3432129 | S84: 5.8985746
A85: Mississippi | B85: HVDC | C85: New | D85: Single | E85: MississippiHVDCNewSingle | O85: 2.7939653 | P85: 3.3838706 | Q85: 3.5853401 | R85: 3.8219722 | S85: 6.3996017
A86: Missouri | B86: HVDC | C86: New | D86: Single | E86: MissouriHVDCNewSingle | O86: 2.3826004 | P86: 2.8142885 | Q86: 2.9524711 | R86: 3.141638 | S86: 5.6876241
A87: Montana | B87: HVDC | C87: New | D87: Single | E87: MontanaHVDCNewSingle | O87: 2.1829096 | P87: 2.5377935 | Q87: 2.6452544 | R87: 2.81138 | S87: 5.3420053
A88: North Dakota | B88: HVDC | C88: New | D88: Single | E88: North DakotaHVDCNewSingle | O88: 2.2336201 | P88: 2.608008 | Q88: 2.7232706 | R88: 2.8952474 | S88: 5.4297735
... A91: Wisconsin | B91: HVDC | C91: New | D91: Single | E91: WisconsinHVDCNewSingle | O91: 2.6739621 | P91: 3.1951684 | Q91: 3.367554 | R91: 3.5863512 | S91: 6.2646432
A92: Illinois | B92: Sub | D92: Upgrade - Add one position (straight or ring bus) | G92: 1.3189067 | H92: 1.5282168 | I92: 1.7183474 | J92: 1.9083994 | K92: 2.2395658 | L92: 3.5580987 | M92: 5.4813849 | N92: 18.368899
A93: Illinois | B93: Sub | D93: Upgrade - Add one position (breaker-and-a-half bus) | G93: 1.8155686 | H93: 2.1145754 | I93: 2.3874809 | J93: 2.6594878 | K93: 3.1585996 | L93: 5.1440423 | M93: 7.6599791 | N93: 23.172074
A94: Illinois | B94: Sub | D94: Upgrade - Add one position (double-breaker bus) | G94: 2.0492268 | H94: 2.3835644 | I94: 2.6893285 | J94: 2.9899468 | K94: 3.5176739 | L94: 5.5930679 | M94: 8.2991105 | N94: 23.978017
A95: Illinois | B95: Sub | D95: Upgrade - Add two positions (straight or ring bus) | G95: 2.6285058 | H95: 3.0461259 | I95: 3.4252717 | J95: 3.8041449 | K95: 4.4651125 | L95: 7.0991207 | M95: 10.939885 | N95: 28.073997
A96: Illinois | B96: Sub | D96: Upgrade - Add two positions (breaker-and-a-half bus) | G96: 3.2765445 | H96: 3.7983948 | I96: 4.2748488 | J96: 4.7502103 | K96: 5.5936566 | L96: 8.9403581 | M96: 13.49899 | N96: 33.352259
A97: Illinois | B97: Sub | D97: Upgrade - Add two positions (double-breaker bus) | G97: 4.0891459 | H97: 4.7568211 | I97: 5.367234 | J97: 5.9672399 | K97: 7.0213287 | L97: 11.169059 | M97: 16.575337 | N97: 39.292234
A98: Illinois | B98: Sub | D98: New - 3 positions (ring bus) | G98: 8.4070294 | H98: 9.3093035 | I98: 10.168049 | J98: 11.002124 | K98: 12.256429 | L98: 17.702324 | M98: 25.687683 | N98: 49.148672
A99: Illinois | B99: Sub | D99: New - 3 positions (breaker-and-a-half bus) | G99: 10.244603 | H99: 11.436269 | I99: 12.56714 | J99: 13.671791 | K99: 15.393864 | L99: 22.502116 | M99: 32.876295 | N99: 62.402126
A100: Illinois | B100: Sub | D100: New - 3 positions (double-breaker bus) | G100: 11.596228 | H100: 12.984179 | I100: 14.301942 | J100: 15.588417 | K100: 17.578309 | L100: 25.851499 | M100: 38.273353 | N100: 72.578267
A101: Illinois | B101: Sub | D101: New - 4 positions (ring bus) | G101: 9.1412867 | H101: 10.162961 | I101: 11.126756 | J101: 12.074181 | K101: 13.582808 | L101: 19.923391 | M101: 28.919143 | N101: 56.041851
A102: Illinois | B102: Sub | D102: New - 4 positions (breaker-and-a-half bus) | G102: 11.013027 | H102: 12.325991 | I102: 13.563809 | J102: 14.783708 | K102: 16.762002 | L102: 24.774432 | M102: 36.167546 | N102: 69.370045
A103: Illinois | B103: Sub | D103: New - 4 positions (double-breaker bus) | G103: 12.744103 | H103: 14.330414 | I103: 15.825264 | J103: 17.296306 | K103: 19.697729 | L103: 29.505715 | M103: 43.422478 | N103: 83.949013
... A109: Illinois | B109: Sub | D109: New - 6 positions (double-breaker bus) | G109: 16.494816 | H109: 18.708702 | I109: 20.695459 | J109: 22.753054 | K109: 26.106782 | L109: 39.539396 | M109: 58.467297 | N109: 113.25402
B110: Sub | D110: HVDC - Line Commutated Converter | O110: 128.65323 | P110: 383.84432 | Q110: 517.88215 | R110: 623.26626 | S110: 776.4463
B111: Sub | D111: HVDC - Voltage Source Converter | O111: 171.92226 | P111: 498.65147 | Q111: 670.18911 | R111: 810.95767 | S111: 987.11068
B112: Sub | D112: Transformer secondary voltage (if applicable) | G112: 1.8155686 | H112: 2.1145754 | I112: 2.3874809 | J112: 2.6594878 | K112: 3.1585996 | L112: 5.1440423 | M112: 7.6599791 | N112: 23.172074
A113: Note: Transformer unit cost; +10% overhead, +30% Contingency, +7.5% AFUDC | B113: Sub | D113: Transformer | E113: 69 kV | G113: 9307.6479 | H113: 7576.887 | I113: 8384.5754 | J113: 8826.881 | K113: 9788.4149 | L113: 12019.173 | M113: 15499.926 | N113: 21807.588
B114: Sub | D114: Transformer | E114: 115 kV | G114: 7576.887 | H114: 10307.643 | I114: 8384.5754 | J114: 8826.881 | K114: 9788.4149 | L114: 11423.022 | M114: 14019.164 | N114: 17942.222
B115: Sub | D115: Transformer | E115: 138 kV | G115: 8384.5754 | H115: 8384.5754 | I115: 11423.022 | J115: 9307.6479 | K115: 9788.4149 | L115: 11423.022 | M115: 14019.164 | N115: 17942.222
B116: Sub | D116: Transformer | E116: 161 kV | G116: 8826.881 | H116: 8826.881 | I116: 9307.6479 | J116: 12653.786 | K116: 10307.643 | L116: 12019.173 | M116: 14749.93 | N116: 17942.222
B117: Sub | D117: Transformer | E117: 230 kV | G117: 9788.4149 | H117: 9788.4149 | I117: 9788.4149 | J117: 10307.643 | K117: 14019.164 | L117: 12019.173 | M117: 14749.93 | N117: 17942.222
...

Sheet Costs over time estimate
A1: MISO
A2: Transmission Line - 5 year construction - convert present year capital cost to nominal cost
A4: Input cells-teal color
F5: Construction cost spend per year allocation
A6: State | D6: Iowa | F6: Year 1 | G6: Year 2 | H6: Year 3 | I6: Year 4 | J6: Year 5
A7: Inflation Rate | D7: 0.025 | F7: 0.01 | G7: 0.04 | H7: 0.35 | I7: 0.35 | J7: =1-SUM(F7:I7) -> 0.25
A8: Project Cost (PC) Present Year | D8: 100000000 | F8: =F$7*D8 -> 1000000 | G8: =G7*D8 -> 4000000 | H8: =H7*D8 -> 35000000 | I8: =I7*D8 -> 35000000 | J8: =J7*D8 -> 25000000
A9: Contingency | C9: 0.2 | D9: =ROUND(D8*C9,0) -> 20000000 | F9: =F7*$D9 -> 200000 | G9: =G7*$D9 -> 800000 | H9: =H7*$D9 -> 7000000 | I9: =I7*$D9 -> 7000000 | J9: =J7*$D9 -> 5000000
A10: AFUDC | C10: 0.075 | D10: =SUM(F10:J10) -> 16173782 | F10: =IF(SUM(F8:F9)>0,(SUM(F8:F9)/2*C10),0) -> 45000 | G10: =IF(SUM(G8:G9)>0,(SUM(G8:G9)/2+SUM($F$11:F11))*$C$10,0) -> 273375 | H10: =IF(SUM(H8:H9)>0,(SUM(H8:H9)/2+SUM($F$11:G11))*$C$10,0) -> 2048878.1 | I10: =IF(SUM(I8:I9)>0,(SUM(I8:I9)/2+SUM($F$11:H11))*$C$10,0) -> 5352544 | J10: =IF(SUM(J8:J9)>0,(SUM(J8:J9)/2+SUM($F$11:I11))*$C$10,0) -> 8453984.8
A11: Total Capital Cost | D11: =SUM(D8:D10) -> 1.3617378e+08 | F11: =SUM(F8:F10) -> 1245000 | G11: =SUM(G8:G10) -> 5073375 | H11: =SUM(H8:H10) -> 44048878 | I11: =SUM(I8:I10) -> 47352544 | J11: =SUM(J8:J10) -> 38453985
A13: PI to In Service cost "Nominal" | D13: =SUM(F13:J13) -> 1.4981767e+08 | F13: =F$11*((1+D$7)^1) -> 1276125 | G13: =G$11*((1+D$7)^2) -> 5330214.6 | H13: =H$11*((1+D$7)^3) -> 47435824 | I13: =I$11*((1+D$7)^4) -> 52268348 | J13: =J$11*((1+D$7)^5) -> 43507154
C14: % increase from current year $ | D14: =(D13-D11)/D11 -> 0.10019465
C15: AFUDC effective % | D15: =D10/SUM(D8:D9) -> 0.13478152 | F15: AFUDC is calculated based on the average spend for the current year plus the cumulative spend from prior years.
H17: 0.071
A18: Year # | B18: Gross Plant Project Cost ISD Yr.$ (PI) | C18: Net Plant Project Cost ISD Yr.$ (PI) | D18: Annual Depreciation Factor | E18: Return Factor subject to decrease in net plant | F18: Expense Factor | G18: Annual Cost to be Recovered | H18: Present Value Discount Rate | I18: Net Present Value Cost
A19: MTEP Year | H19: 1
A20: 1 | H20: =H19/(1+H$17) -> 0.93370682
A21: =A20+1 -> 2 | H21: =H20/(1+H$17) -> 0.87180842
A22: =A21+1 -> 3 | H22: =H21/(1+H$17) -> 0.81401346
A23: =A22+1 -> 4 | H23: =H22/(1+H$17) -> 0.76004992
A24: =A23+1 -> 5 | E24: =VLOOKUP(D6,'Cost over time data'!A2:C18,3,FALSE()) -> 0.0844346 | H24: =H23/(1+H$17) -> 0.70966379
A25: =A24+1 -> 6 | B25: =D13 -> 1.4981767e+08 | C25: =B25*(1-SUM($D$25:D25)) -> 1.4607222e+08 | D25: =1/40 -> 0.025 | E25: =(C25/B25)*$E$24 -> 0.082323735 | F25: =VLOOKUP(D6,'Cost over time data'!A2:C18,2,FALSE()) -> 0.034248163 | G25: =B25*SUM(D25:F25) -> 21209971 | H25: =H24/(1+H$17) -> 0.66261792 | I25: =G25*H25 -> 14054107
A26: =A25+1 -> 7 | B26: =B25 -> 1.4981767e+08 | C26: =B26*(1-SUM($D$25:D26)) -> 1.4232678e+08 | D26: =D25 -> 0.025 | E26: =(C26/B26)*$E$24 -> 0.08021287 | F26: =F25 -> 0.034248163 | G26: =B26*SUM(D26:F26) -> 20893726 | H26: =H25/(1+H$17) -> 0.61869087 | I26: =G26*H26 -> 12926758
A27: =A26+1 -> 8 | B27: =B26 -> 1.4981767e+08 | C27: =B27*(1-SUM($D$25:D27)) -> 1.3858134e+08 | D27: =D26 -> 0.025 | E27: =(C27/B27)*$E$24 -> 0.078102005 | F27: =F26 -> 0.034248163 | G27: =B27*SUM(D27:F27) -> 20577481 | H27: =H26/(1+H$17) -> 0.57767588 | I27: =G27*H27 -> 11887115
A28: =A27+1 -> 9 | B28: =B27 -> 1.4981767e+08 | C28: =B28*(1-SUM($D$25:D28)) -> 1.348359e+08 | D28: =D27 -> 0.025 | E28: =(C28/B28)*$E$24 -> 0.07599114 | F28: =F27 -> 0.034248163 | G28: =B28*SUM(D28:F28) -> 20261237 | H28: =H27/(1+H$17) -> 0.53937991 | I28: =G28*H28 -> 10928504
A29: =A28+1 -> 10 | B29: =B28 -> 1.4981767e+08 | C29: =B29*(1-SUM($D$25:D29)) -> 1.3109046e+08 | D29: =D28 -> 0.025 | E29: =(C29/B29)*$E$24 -> 0.073880275 | F29: =F28 -> 0.034248163 | G29: =B29*SUM(D29:F29) -> 19944992 | H29: =H28/(1+H$17) -> 0.50362269 | I29: =G29*H29 -> 10044750
A30: =A29+1 -> 11 | B30: =B29 -> 1.4981767e+08 | C30: =B30*(1-SUM($D$25:D30)) -> 1.2734502e+08 | D30: =D29 -> 0.025 | E30: =(C30/B30)*$E$24 -> 0.07176941 | F30: =F29 -> 0.034248163 | G30: =B30*SUM(D30:F30) -> 19628747 | H30: =H29/(1+H$17) -> 0.47023594 | I30: =G30*H30 -> 9230142.3
A31: =A30+1 -> 12 | B31: =B30 -> 1.4981767e+08 | C31: =B31*(1-SUM($D$25:D31)) -> 1.2359957e+08 | D31: =D30 -> 0.025 | E31: =(C31/B31)*$E$24 -> 0.069658545 | F31: =F30 -> 0.034248163 | G31: =B31*SUM(D31:F31) -> 19312502 | H31: =H30/(1+H$17) -> 0.4390625 | I31: =G31*H31 -> 8479395.5
A32: =A31+1 -> 13 | B32: =B31 -> 1.4981767e+08 | C32: =B32*(1-SUM($D$25:D32)) -> 1.1985413e+08 | D32: =D31 -> 0.025 | E32: =(C32/B32)*$E$24 -> 0.06754768 | F32: =F31 -> 0.034248163 | G32: =B32*SUM(D32:F32) -> 18996257 | H32: =H31/(1+H$17) -> 0.40995565 | I32: =G32*H32 -> 7787623
A33: =A32+1 -> 14 | B33: =B32 -> 1.4981767e+08 | C33: =B33*(1-SUM($D$25:D33)) -> 1.1610869e+08 | D33: =D32 -> 0.025 | E33: =(C33/B33)*$E$24 -> 0.065436815 | F33: =F32 -> 0.034248163 | G33: =B33*SUM(D33:F33) -> 18680012 | H33: =H32/(1+H$17) -> 0.38277839 | I33: =G33*H33 -> 7150305
A34: =A33+1 -> 15 | B34: =B33 -> 1.4981767e+08 | C34: =B34*(1-SUM($D$25:D34)) -> 1.1236325e+08 | D34: =D33 -> 0.025 | E34: =(C34/B34)*$E$24 -> 0.06332595 | F34: =F33 -> 0.034248163 | G34: =B34*SUM(D34:F34) -> 18363767 | H34: =H33/(1+H$17) -> 0.35740279 | I34: =G34*H34 -> 6563261.7
A35: =A34+1 -> 16 | B35: =B34 -> 1.4981767e+08 | C35: =B35*(1-SUM($D$25:D35)) -> 1.0861781e+08 | D35: =D34 -> 0.025 | E35: =(C35/B35)*$E$24 -> 0.061215085 | F35: =F34 -> 0.034248163 | G35: =B35*SUM(D35:F35) -> 18047523 | H35: =H34/(1+H$17) -> 0.33370942 | I35: =G35*H35 -> 6022628.3
A36: =A35+1 -> 17 | B36: =B35 -> 1.4981767e+08 | C36: =B36*(1-SUM($D$25:D36)) -> 1.0487237e+08 | D36: =D35 -> 0.025 | E36: =(C36/B36)*$E$24 -> 0.05910422 | F36: =F35 -> 0.034248163 | G36: =B36*SUM(D36:F36) -> 17731278 | H36: =H35/(1+H$17) -> 0.31158676 | I36: =G36*H36 -> 5524831.4
A37: =A36+1 -> 18 | B37: =B36 -> 1.4981767e+08 | C37: =B37*(1-SUM($D$25:D37)) -> 1.0112692e+08 | D37: =D36 -> 0.025 | E37: =(C37/B37)*$E$24 -> 0.056993355 | F37: =F36 -> 0.034248163 | G37: =B37*SUM(D37:F37) -> 17415033 | H37: =H36/(1+H$17) -> 0.29093068 | I37: =G37*H37 -> 5066567.4
... A44: =A43+1 -> 25 | B44: =B43 -> 1.4981767e+08 | C44: =B44*(1-SUM($D$25:D44)) -> 74908833 | D44: =D43 -> 0.025 | E44: =(C44/B44)*$E$24 -> 0.0422173 | F44: =F43 -> 0.034248163 | G44: =B44*SUM(D44:F44) -> 15201319 | H44: =H43/(1+H$17) -> 0.17999616 | I44: =G44*H44 -> 2736178.9
I45: =SUM(I25:I44) -> 1.4103481e+08

Sheet Cost over time data
A1: Expense Factor and Return Factor (by State)
A2: State | B2: Expense Factor | C2: Return Factor
A3: Arkansas | B3: 0.029611352 | C3: 0.081004158
A4: Illinois | B4: 0.036897768 | C4: 0.082875308
A5: Indiana | B5: 0.031598557 | C5: 0.082251591
A6: Iowa | B6: 0.034248163 | C6: 0.0844346
A7: Kentucky | B7: 0.030815719 | C7: 0.0806923
A8: Louisiana | B8: 0.02756393 | C8: 0.081939733
A9: Michigan | B9: 0.036235367 | C9: 0.0806923
A10: Minnesota | B10: 0.032802923 | C10: 0.083062423
A11: Mississippi | B11: 0.029611352 | C11: 0.080068583
A12: Missouri | B12: 0.031959867 | C12: 0.080848229
A13: Montana | B13: 0.03147812 | C13: 0.081160087
A14: North Dakota | B14: 0.035031001 | C14: 0.080193326
... A17: Wisconsin | B17: 0.037078423 | C17: 0.081877361
A18: Average | B18: =AVERAGE(B3:B17) -> 0.0331 | C18: =AVERAGE(C3:C17) -> 0.081
